arcadia/__init__.py
arcadia/models.py
arcadia-0.0.1.dist-info/DESCRIPTION.rst
arcadia-0.0.1.dist-info/METADATA
arcadia-0.0.1.dist-info/RECORD
arcadia-0.0.1.dist-info/WHEEL
arcadia-0.0.1.dist-info/metadata.json
arcadia-0.0.1.dist-info/top_level.txt
