Metadata-Version: 2.0
Name: arcadia
Version: 0.0.1
Summary: Online store for django
Home-page: UNKNOWN
Author: Dmitriy Sergeev
Author-email: dmitriy.93.sergeev@gmail.com
License: MIT
Platform: UNKNOWN
Classifier: License :: OSI Approved :: MIT License
Classifier: Programming Language :: Python :: 2.7
